salad_cloud_transcription_sdk/__init__.py
salad_cloud_transcription_sdk/sdk.py
salad_cloud_transcription_sdk/sdk_async.py
salad_cloud_transcription_sdk/models/__init__.py
salad_cloud_transcription_sdk/models/file_operation_response.py
salad_cloud_transcription_sdk/models/transcription_engine.py
salad_cloud_transcription_sdk/models/transcription_job_file_output.py
salad_cloud_transcription_sdk/models/transcription_job_input.py
salad_cloud_transcription_sdk/models/transcription_job_output.py
salad_cloud_transcription_sdk/models/transcription_request.py
salad_cloud_transcription_sdk/models/transcription_webhook_payload.py
salad_cloud_transcription_sdk/models/utils/__init__.py
salad_cloud_transcription_sdk/models/utils/base_model.py
salad_cloud_transcription_sdk/models/utils/cast_models.py
salad_cloud_transcription_sdk/models/utils/json_map.py
salad_cloud_transcription_sdk/models/utils/one_of_base_model.py
salad_cloud_transcription_sdk/models/utils/sentinel.py
salad_cloud_transcription_sdk/net/__init__.py
salad_cloud_transcription_sdk/net/environment/__init__.py
salad_cloud_transcription_sdk/net/environment/environment.py
salad_cloud_transcription_sdk/net/headers/__init__.py
salad_cloud_transcription_sdk/net/headers/api_key_auth.py
salad_cloud_transcription_sdk/net/headers/base_header.py
salad_cloud_transcription_sdk/net/request_chain/__init__.py
salad_cloud_transcription_sdk/net/request_chain/request_chain.py
salad_cloud_transcription_sdk/net/request_chain/handlers/__init__.py
salad_cloud_transcription_sdk/net/request_chain/handlers/base_handler.py
salad_cloud_transcription_sdk/net/request_chain/handlers/http_handler.py
salad_cloud_transcription_sdk/net/request_chain/handlers/retry_handler.py
salad_cloud_transcription_sdk/net/transport/__init__.py
salad_cloud_transcription_sdk/net/transport/request.py
salad_cloud_transcription_sdk/net/transport/request_error.py
salad_cloud_transcription_sdk/net/transport/response.py
salad_cloud_transcription_sdk-1.0.0a1.dist-info/licenses/LICENSE
salad_cloud_transcription_sdk-1.0.0a1.dist-info/METADATA
salad_cloud_transcription_sdk-1.0.0a1.dist-info/WHEEL
salad_cloud_transcription_sdk-1.0.0a1.dist-info/top_level.txt
salad_cloud_transcription_sdk-1.0.0a1.dist-info/RECORD
