Metadata-Version: 2.4
Name: salad-cloud-transcription-sdk
Version: 1.0.0a1
Summary: The SaladCloud Transcription SDK. Please refer to the [SaladCloud Transcription API Documentation](https://docs.salad.com/transcription/) for more details.
License: MIT
Project-URL: Homepage, https://github.com/saladtechnologies/salad-cloud-transcription-sdk-python
Project-URL: Documentation, https://docs.salad.com
Project-URL: Repository, https://github.com/SaladTechnologies/salad-cloud-transcription-sdk-python.git
Project-URL: Issues, https://github.com/SaladTechnologies/salad-cloud-transcription-sdk-python/issues
Classifier: Development Status :: 3 - Alpha
Classifier: Intended Audience :: Developers
Classifier: License :: OSI Approved :: MIT License
Classifier: Operating System :: OS Independent
Classifier: Programming Language :: Python
Classifier: Programming Language :: Python :: 3
Classifier: Programming Language :: Python :: 3 :: Only
Classifier: Programming Language :: Python :: 3.9
Classifier: Programming Language :: Python :: 3.10
Classifier: Programming Language :: Python :: 3.11
Classifier: Programming Language :: Python :: 3.12
Classifier: Topic :: Internet
Classifier: Topic :: Multimedia :: Sound/Audio :: Speech
Classifier: Topic :: Software Development
Classifier: Topic :: Software Development :: Libraries
Requires-Python: >=3.9
License-File: LICENSE
Requires-Dist: requests>=2.31.0
Requires-Dist: salad-cloud-sdk<0.10.0,>=0.9.0a8
Requires-Dist: pytest-asyncio<0.27.0,>=0.26.0
Dynamic: license-file
